yooink/__init__.py
yooink/ooi_data_summary.py
yooink/utils.py
yooink/api/__init__.py
yooink/api/client.py
yooink/data/__init__.py
yooink/data/data_combinations.csv
yooink/data/data_manager.py
yooink/data/ooi_data.parquet
yooink/request/__init__.py
yooink/request/data_fetcher.py
yooink/request/m2m_urls.yml
yooink/request/request_manager.py
yooink-0.1.9.dist-info/METADATA
yooink-0.1.9.dist-info/WHEEL
yooink-0.1.9.dist-info/licenses/LICENSE
yooink-0.1.9.dist-info/RECORD
