Metadata-Version: 2.4
Name: yooink
Version: 0.1.9
Summary: A package for accessing OOI data via the m2m protocol
Project-URL: Repository, https://github.com/Waveform-Analytics/yooink
Project-URL: Documentation, https://waveform-analytics.github.io/yooink/
Project-URL: Issues, https://github.com/Waveform-Analytics/yooink/issues
Author-email: Michelle Weirathmueller <michelle@waveformanalytics.com>
License: MIT License
License-File: LICENSE
Keywords: OOI,ocean observatory data
Classifier: License :: OSI Approved :: MIT License
Classifier: Operating System :: OS Independent
Classifier: Programming Language :: Python :: 3
Requires-Python: >=3.9
Requires-Dist: beautifulsoup4>=4.13.3
Requires-Dist: h5netcdf>=1.5.0
Requires-Dist: h5py>=3.13.0
Requires-Dist: ipykernel>=6.29.5
Requires-Dist: jupyterlab>=4.3.5
Requires-Dist: munch>=4.0.0
Requires-Dist: numpy>=2.0.2
Requires-Dist: pandas>=2.2.3
Requires-Dist: pyarrow>=19.0.1
Requires-Dist: python-dateutil>=2.9.0.post0
Requires-Dist: pytz>=2025.1
Requires-Dist: pyyaml>=6.0.2
Requires-Dist: requests>=2.32.3
Requires-Dist: tomlkit>=0.13.2
Requires-Dist: tqdm>=4.67.1
Requires-Dist: xarray>=2024.7.0
